{
  "resource": "Events",
  "resource_explanation": "El Plano events API.\n\nEvent attributes :\n\n - `title` - Represents event name.\n - `description` - Represents event detailed description.\n - `status` - Represents event current status.\n   - `confirmed` - The event is confirmed. This is the default status.\n   - `tentative` - The event is tentatively confirmed.\n   - `cancelled` - The event is cancelled (deleted).\n\n - `recurrence` - Represents recurrence rules.\n - `timezone` - Timezone settings.\n - `start_at` - Represents when event starts.\n - `end_at` - Represents when event ends.\n - timestamps\n\n Also, includes reference to the event creator and attached course.\n",
  "http_method": "POST",
  "route": "api/v1/events",
  "description": "CREATE : Creates new event",
  "explanation": "Create and return created event.\n",
  "parameters": [
    {
      "scope": [
        "dta",
        "attributes"
      ],
      "requred": true,
      "name": "title",
      "description": "Event title(human readable identity)"
    },
    {
      "scope": [
        "dta",
        "attributes"
      ],
      "name": "description",
      "description": "Detailed event description"
    },
    {
      "scope": [
        "dta",
        "attributes"
      ],
      "name": "recurrence",
      "description": "Recurrence rules if an event is recurrent"
    },
    {
      "scope": [
        "dta",
        "attributes"
      ],
      "requred": true,
      "name": "start_at",
      "description": "Event start date"
    },
    {
      "scope": [
        "dta",
        "attributes"
      ],
      "requred": true,
      "name": "end_at",
      "description": "Event end date"
    },
    {
      "scope": [
        "dta",
        "attributes"
      ],
      "requred": true,
      "name": "timezone",
      "description": "Event timezone"
    },
    {
      "scope": [
        "dta",
        "attributes"
      ],
      "name": "course",
      "description": "The course to which the event is attached. Included in \"relationships\" category"
    }
  ],
  "response_fields": [

  ],
  "requests": [
    {
      "request_method": "POST",
      "request_path": "api/v1/events",
      "request_body": "{\"data\":{\"type\":\"event\",\"attributes\":{\"title\":\"Soluta quo et.\",\"description\":\"Soluta facere qui. Praesentium et est. Amet reiciendis aut. Corporis aspernatur rem. Quia voluptatem culpa.\",\"status\":\"cancelled\",\"start_at\":\"2019-03-15\",\"end_at\":\"2019-03-17\",\"timezone\":\"Etc/GMT+12\",\"recurrence\":[\"EXDATE;VALUE=DATE:20150610\",\"RDATE;VALUE=DATE:20150609,20150611\",\"RRULE:FREQ=DAILY;UNTIL=20150628;INTERVAL=3\"]},\"relationships\":{\"course\":{\"data\":{\"id\":6,\"type\":\"course\"}}}}}",
      "request_headers": {
        "Accept": "application/vnd.api+json",
        "Content-Type": "application/vnd.api+json",
        "Authorization": "Bearer 3f32c23d4403f9d9c8d7493df43a461b3458ac748053c901c6fe78078cfc133a",
        "Host": "example.org",
        "Cookie": ""
      },
      "request_query_parameters": {
      },
      "request_content_type": "application/vnd.api+json",
      "response_status": 201,
      "response_status_text": "Created",
      "response_body": "{\n  \"data\": {\n    \"id\": \"3\",\n    \"type\": \"event\",\n    \"attributes\": {\n      \"title\": \"Soluta quo et.\",\n      \"description\": \"Soluta facere qui. Praesentium et est. Amet reiciendis aut. Corporis aspernatur rem. Quia voluptatem culpa.\",\n      \"status\": \"cancelled\",\n      \"recurrence\": [\n        \"EXDATE;VALUE=DATE:20150610\",\n        \"RDATE;VALUE=DATE:20150609,20150611\",\n        \"RRULE:FREQ=DAILY;UNTIL=20150628;INTERVAL=3\"\n      ],\n      \"start_at\": \"2019-03-15T00:00:00.000Z\",\n      \"end_at\": \"2019-03-17T00:00:00.000Z\",\n      \"timezone\": \"Etc/GMT+12\",\n      \"created_at\": \"2019-03-16T16:21:04.562Z\",\n      \"updated_at\": \"2019-03-16T16:21:04.562Z\"\n    },\n    \"relationships\": {\n      \"creator\": {\n        \"data\": {\n          \"id\": \"11\",\n          \"type\": \"student\"\n        }\n      },\n      \"course\": {\n        \"data\": {\n          \"id\": \"6\",\n          \"type\": \"course\"\n        }\n      }\n    }\n  }\n}",
      "response_headers": {
        "Page-Title": "El+Plano",
        "X-Frame-Options": "DENY",
        "X-XSS-Protection": "1; mode=block",
        "X-Content-Type-Options": "nosniff",
        "Cache-Control": "max-age=0, private, must-revalidate, no-store",
        "Pragma": "no-cache",
        "Content-Type": "application/json; charset=utf-8",
        "ETag": "W/\"ad9536e383f213fd465ad82bd10a4b6e\"",
        "X-Request-Id": "2ebfece3-796b-4c5a-b881-62d9d3642f79",
        "X-Runtime": "0.010127",
        "Vary": "Origin",
        "Content-Length": "634"
      },
      "response_content_type": "application/json; charset=utf-8",
      "curl": "curl \"http://localhost:3000/api/v1/events\" -d '{\"data\":{\"type\":\"event\",\"attributes\":{\"title\":\"Soluta quo et.\",\"description\":\"Soluta facere qui. Praesentium et est. Amet reiciendis aut. Corporis aspernatur rem. Quia voluptatem culpa.\",\"status\":\"cancelled\",\"start_at\":\"2019-03-15\",\"end_at\":\"2019-03-17\",\"timezone\":\"Etc/GMT+12\",\"recurrence\":[\"EXDATE;VALUE=DATE:20150610\",\"RDATE;VALUE=DATE:20150609,20150611\",\"RRULE:FREQ=DAILY;UNTIL=20150628;INTERVAL=3\"]},\"relationships\":{\"course\":{\"data\":{\"id\":6,\"type\":\"course\"}}}}}' -X POST \\\n\t-H \"Accept: application/vnd.api+json\" \\\n\t-H \"Content-Type: application/vnd.api+json\" \\\n\t-H \"Authorization: Bearer 3f32c23d4403f9d9c8d7493df43a461b3458ac748053c901c6fe78078cfc133a\" \\\n\t-H \"Host: example.org\" \\\n\t-H \"Cookie: \""
    }
  ]
}