{
  "resource": "Uploads",
  "resource_explanation": null,
  "http_method": "POST",
  "route": "uploads",
  "description": "CREATE : Upload file",
  "explanation": "Returns uploaded file identity and its metadata\n\nUploaded file metadata attributes :\n\n  - `id` - Represents unique uploaded file identity.\n  - `storage` - Represents file storage type.\n  - `metadata` - Represents uploaded file metadata(name, size, e.t.c.).\n    - `filename` - Represents name of the uploaded file.\n    - `size` - Represents size of the uploaded file(bytes).\n    - `mime_type` - Represents MIME(Multipurpose Internet Mail Extensions or MIME) type of the uploaded file.\n",
  "parameters": [
    {
      "scope": "upload",
      "required": true,
      "name": "type",
      "description": "Uploader type"
    },
    {
      "scope": "upload",
      "required": true,
      "name": "file",
      "description": "The file that needs to be uploaded"
    }
  ],
  "response_fields": [

  ],
  "requests": [
    {
      "request_method": "POST",
      "request_path": "uploads",
      "request_body": "{\"upload\":{\"type\":\"avatar\",\"file\":{\"original_filename\":\"dk.png\",\"tempfile\":\"#\\u003cFile:0x000056416821cff0\\u003e\",\"content_type\":null}}}",
      "request_headers": {
        "Accept": "application/vnd.api+json",
        "Content-Type": "application/vnd.api+json",
        "Authorization": "Bearer 71cd5c73e9205cf9d9ad3288b9cc5aacb4fbf0d570c290bacb76a67b2b4e1117",
        "Host": "example.org",
        "Cookie": ""
      },
      "request_query_parameters": {
      },
      "request_content_type": "application/vnd.api+json",
      "response_status": 201,
      "response_status_text": "Created",
      "response_body": "{\n  \"id\": \"344f98a5e8c879851116c54e9eb5e610.jpg\",\n  \"storage\": \"cache\",\n  \"metadata\": {\n    \"filename\": \"dk.png\",\n    \"size\": 1062,\n    \"mime_type\": \"image/png\"\n  }\n}",
      "response_headers": {
        "Page-Title": "El+Plano",
        "X-Frame-Options": "DENY",
        "X-XSS-Protection": "1; mode=block",
        "X-Content-Type-Options": "nosniff",
        "Cache-Control": "max-age=0, private, must-revalidate, no-store",
        "Pragma": "no-cache",
        "Content-Type": "application/json; charset=utf-8",
        "ETag": "W/\"8ecd08c9c8b429daec96b39817a22ceb\"",
        "X-Request-Id": "4ef4d4da-0cb9-43ad-a2f8-aa8b1e82a059",
        "X-Runtime": "0.010957",
        "Vary": "Origin",
        "Content-Length": "132"
      },
      "response_content_type": "application/json; charset=utf-8",
      "curl": "curl \"http://localhost:3000/uploads\" -d '{\"upload\":{\"type\":\"avatar\",\"file\":{\"original_filename\":\"dk.png\",\"tempfile\":\"#\\u003cFile:0x000056416821cff0\\u003e\",\"content_type\":null}}}' -X POST \\\n\t-H \"Accept: application/vnd.api+json\" \\\n\t-H \"Content-Type: application/vnd.api+json\" \\\n\t-H \"Authorization: Bearer 71cd5c73e9205cf9d9ad3288b9cc5aacb4fbf0d570c290bacb76a67b2b4e1117\" \\\n\t-H \"Host: example.org\" \\\n\t-H \"Cookie: \""
    }
  ]
}